[
  {
    "title": "BFDI 1a: Take the Plunge",
    "show": "BFDI",
    "youtubeId": "YQa2-DY7Y0Q",
    "noEmbed": true
  },
  {
    "title": "BFDI 1b: Take the Plunge",
    "show": "BFDI",
    "youtubeId": "8LY0o_CgPR8"
  },
  {
    "title": "BFDI 2: Barriers and Pitfalls",
    "show": "BFDI",
    "youtubeId": "JfzEO9-Zlhw&t"
  },
  {
    "title": "BFDI 3: Are You Smarter Than a Snowball?",
    "show": "BFDI",
    "youtubeId": "rhkgOXksmaY"
  },
  {
    "title": "BFDI 4: Sweet Tooth",
    "show": "BFDI",
    "youtubeId": "cdmVPHdpECM"
  },
  {
    "title": "BFDI 5: Bridge Crossing",
    "show": "BFDI",
    "youtubeId": "xHI-iKm31us"
  },
  {
    "title": "BFDI 6: Power of Three",
    "show": "BFDI",
    "youtubeId": "6vGgsXO57bs&t"
  },
  {
    "title": "BFDI 7: Puzzling Mysteries",
    "show": "BFDI",
    "youtubeId": "Ze1p7bYXw0g"
  },
  {
    "title": "BFDIA 25: She Deserves This",
    "show": "BFDI",
    "youtubeId": "hTK2jHPtv5o"
  },
  {
    "title": "Inanimate Insanity 1: The Crappy Cliff",
    "show": "II",
    "youtubeId": "lcGtU2eYeyU"
  },
  {
    "title": "Inanimate Insanity 2: A Lemony Lesson",
    "show": "II",
    "youtubeId": "iHQWL7CV4Sk"
  },
  {
    "title": "ONE 1: Freefall",
    "show": "ONE",
    "youtubeId": "8Gu0hjkq1Zg"
  },
  {
    "title": "Animatic Battle 1: M Is for Magic",
    "show": "AB",
    "youtubeId": "CjbUT7C5VY8"
  },
  {
    "title": "Bean's Show 1: Forget The Secondly",
    "show": "BS",
    "youtubeId": "k6EQHD4oD9I"
  },
  {
    "title": "The Nightly Manor: Part 1 - Visitors, Invited",
    "show": "TNM",
    "youtubeId": "T1w9gjxShbo"
  },
  {
    "title": "Object Fool 1: Haha You Thought It Was GGG HAHAHA",
    "show": "OF",
    "youtubeId": "X-sVrwbqIy8"
  },
  {
    "title": "IT'S TIME FOR THE [1:00] - Who's Jason??",
    "show": "ITFT",
    "youtubeId": "kvHc3e87Bfw"
  }
]
